s3_sdk/__init__.py
s3_sdk/s3_client.py
tests/__init__.py
tests/test_s3_client.py
s3_sdk-0.1.5.dist-info/METADATA
s3_sdk-0.1.5.dist-info/WHEEL
s3_sdk-0.1.5.dist-info/top_level.txt
s3_sdk-0.1.5.dist-info/RECORD
