Metadata-Version: 2.4
Name: s3_sdk
Version: 0.1.5
Summary: A simple SDK for interacting with AWS S3
Home-page: https://github.com/GiattiChen
Author: Giatti Chen
Author-email: chenjieting@baidu.com
Classifier: Programming Language :: Python :: 3
Classifier: License :: OSI Approved :: MIT License
Classifier: Operating System :: OS Independent
Requires-Dist: boto3>=1.26.0
Dynamic: author
Dynamic: author-email
Dynamic: classifier
Dynamic: description
Dynamic: description-content-type
Dynamic: home-page
Dynamic: requires-dist
Dynamic: summary
